minimal_activitypub/__init__.py
minimal_activitypub/client_2_server.py
minimal_activitypub-1.5.5.dist-info/WHEEL
minimal_activitypub-1.5.5.dist-info/METADATA
minimal_activitypub-1.5.5.dist-info/RECORD
