Metadata-Version: 2.3
Name: minimal-activitypub
Version: 1.5.5
Summary: Minimal inplementation of ActivityPub Interface
Author: marvin8
Author-email: marvin8 <marvin8@tuta.io>
License: AGPL-3.0-or-later
Classifier: Development Status :: 5 - Production/Stable
Classifier: Intended Audience :: Developers
Classifier: Operating System :: OS Independent
Classifier: Programming Language :: Python
Classifier: Programming Language :: Python :: 3.10
Classifier: Programming Language :: Python :: 3.11
Classifier: Programming Language :: Python :: 3.12
Classifier: Programming Language :: Python :: 3.13
Classifier: Topic :: Software Development :: Libraries :: Python Modules
Requires-Dist: httpx[http2,zstd]~=0.28.1
Requires-Dist: h11~=0.16.0
Requires-Dist: h2~=4.3.0
Requires-Dist: pytz~=2025.2
Requires-Dist: whenever~=0.9.4
Requires-Python: >=3.10, <3.14
Project-URL: Changelog, https://codeberg.org/MarvinsMastodonTools/minimal-activitypub/src/branch/main/CHANGELOG.md
Project-URL: Documentation, https://marvinsmastodontools.codeberg.page/minimal-activitypub/
Project-URL: Issues, https://codeberg.org/MarvinsMastodonTools/minimal-activitypub/issues
Project-URL: Source, https://codeberg.org/MarvinsMastodonTools/minimal-activitypub
